LICENSE
setup.py
sprdbclient/__init__.py
sprdbclient/client.py
sprdbclient/config.py
sprdbclient.egg-info/PKG-INFO
sprdbclient.egg-info/SOURCES.txt
sprdbclient.egg-info/dependency_links.txt
sprdbclient.egg-info/top_level.txt